LICENSE.md
README.md
setup.py
src/bulum/__init__.py
src/bulum/demo.py
src/bulum/test_circular_import.py
src/bulum/version.py
src/bulum.egg-info/PKG-INFO
src/bulum.egg-info/SOURCES.txt
src/bulum.egg-info/dependency_links.txt
src/bulum.egg-info/requires.txt
src/bulum.egg-info/top_level.txt
src/bulum/clim/__init__.py
src/bulum/clim/clim.py
src/bulum/io/__init__.py
src/bulum/io/csv_io.py
src/bulum/io/general_io.py
src/bulum/io/idx_io.py
src/bulum/io/idx_io_native.py
src/bulum/io/iqqm_out_reader.py
src/bulum/io/lqn_io.py
src/bulum/io/res_csv_io.py
src/bulum/maps/__init__.py
src/bulum/maps/station_maps.py
src/bulum/plots/__init__.py
src/bulum/plots/altair_plots.py
src/bulum/plots/ensemble_altair_plots.py
src/bulum/plots/node_diagrams.py
src/bulum/plots/plot_functions.py
src/bulum/plots/plotly_helpers.py
src/bulum/plots/tests/__init__.py
src/bulum/plots/tests/test_plot_functions.py
src/bulum/stats/__init__.py
src/bulum/stats/aggregate_stats.py
src/bulum/stats/ensemble_stats.py
src/bulum/stats/negflo.py
src/bulum/stats/negflo_helpers.py
src/bulum/stats/reliability_stats_class.py
src/bulum/stats/stochastic_data_check.py
src/bulum/stats/storage_level_assessment.py
src/bulum/stats/swflo2s/__init__.py
src/bulum/stats/swflo2s/swflo2s.py
src/bulum/stoch/__init__.py
src/bulum/stoch/analyse.py
src/bulum/stoch/generate.py
src/bulum/trans/__init__.py
src/bulum/trans/transformers.py
src/bulum/utils/__init__.py
src/bulum/utils/dataframe_extensions.py
src/bulum/utils/dataframe_functions.py
src/bulum/utils/datetime_functions.py
src/bulum/utils/interpolation.py