Metadata-Version: 2.2
Name: bulum
Version: 0.3.2
Summary: Open source python library for assessing hydrologic model results in Queensland
Home-page: https://github.com/odhydrology/bulum
Author: Chas Egan
Author-email: chas@odhydrology.com
Classifier: Programming Language :: Python :: 3
Classifier: Operating System :: OS Independent
Requires-Python: >=3.9
License-File: LICENSE.md
Requires-Dist: altair[all]>=5.5.0
Requires-Dist: folium>=0.14
Requires-Dist: matplotlib>=3.8.3
Requires-Dist: numpy>=1.26.4
Requires-Dist: pandas>=2.2.0
Requires-Dist: plotly>=5.18.0
Dynamic: author
Dynamic: author-email
Dynamic: classifier
Dynamic: description
Dynamic: description-content-type
Dynamic: home-page
Dynamic: requires-dist
Dynamic: requires-python
Dynamic: summary
